run_pylint.py
src/autogpt_plugins/__init__.py
src/autogpt_plugins/twitter/__init__.py
agpt_plugins-0.0.2.dist-info/METADATA
agpt_plugins-0.0.2.dist-info/WHEEL
agpt_plugins-0.0.2.dist-info/licenses/LICENSE
agpt_plugins-0.0.2.dist-info/RECORD
